{
    "00-l-00": {
        "venue": "Building A, Room 101",
        "from": 700,
        "to": 730,
        "timetable": "00-t-01",
        "unit": "00-u-00",
        "repeat_to": "2023-05-05",
        "created": "2023-05-05",
        "last_modified": "2023-06-03",
        "day_of_week": 0
    },
    "00-l-01": {
        "venue": "Building B, Room 202",
        "from": 900,
        "to": 1130,
        "timetable": "00-t-01",
        "unit": "00-u-01",
        "repeat_to": "2023-05-05",
        "created": "2023-05-05",
        "last_modified": "2023-06-04",
        "day_of_week": 0
    },
    "00-l-02": {
        "venue": "Building C, Room 303",
        "from": 700,
        "to": 730,
        "timetable": "00-t-01",
        "unit": "00-u-02",
        "repeat_to": "2023-05-05",
        "created": "2023-05-05",
        "last_modified": "2023-06-05",
        "day_of_week": 1
    },
    "00-l-03": {
        "venue": "Building D, Room 404",
        "from": 1400,
        "to": 1600,
        "timetable": "00-t-01",
        "unit": "00-u-03",
        "repeat_to": "2023-05-05",
        "created": "2023-05-05",
        "last_modified": "2023-06-06",
        "day_of_week": 2
    },
    "00-l-04": {
        "venue": "Building E, Room 505",
        "from": 800,
        "to": 1000,
        "timetable": "00-t-01",
        "unit": "00-u-04",
        "repeat_to": "2023-05-05",
        "created": "2023-05-05",
        "last_modified": "2023-06-07",
        "day_of_week": 3
    },
    "00-l-05": {
        "venue": "Building F, Room 606",
        "from": 700,
        "to": 730,
        "timetable": "00-t-01",
        "unit": "00-u-05",
        "repeat_to": "2023-05-05",
        "created": "2023-05-05",
        "last_modified": "2023-06-08",
        "day_of_week": 4
    },
    "00-l-06": {
        "venue": "Building G, Room 707",
        "from": 800,
        "to": 1100,
        "timetable": "00-t-00",
        "description": "",
        "unit": "00-u-06",
        "repeat_to": "2023-05-05",
        "created": "2023-05-05",
        "last_modified": "2023-06-09",
        "day_of_week": 0
    },
    "00-l-07": {
        "venue": "Building H, Room 808",
        "from": 1100,
        "to": 1300,
        "timetable": "00-t-00",
        "unit": "00-u-07",
        "repeat_to": "2023-05-05",
        "created": "2023-05-05",
        "last_modified": "2023-06-10",
        "day_of_week": 0
    },
    "00-l-08": {
        "venue": "Building I, Room 909",
        "from": 900,
        "to": 1100,
        "timetable": "00-t-00",
        "unit": "00-u-08",
        "repeat_to": "2023-05-05",
        "created": "2023-05-05",
        "last_modified": "2023-06-11",
        "day_of_week": 1
    },
    "00-l-09": {
        "venue": "Building J, Room 1010",
        "from": 1100,
        "to": 1300,
        "timetable": "00-t-00",
        "unit": "00-u-09",
        "repeat_to": "2023-05-05",
        "created": "2023-05-05",
        "last_modified": "2023-06-12",
        "day_of_week": 2
    }
}
